{
  "_meta": {
    "version": "2026.2",
    "updated": "2026-02-22",
    "note": "v2: aggiunto campo attrs a cavi, connettori, hawse, contenitori per query dinamiche wizard."
  },
  "motori": {
    "CM4": {
      "label": "CM4",
      "desc": "Cablemaster CM-4",
      "sub": "Cavo Ø 13–20mm · 12V o 24V DC",
      "tensioni": {
        "12V": "05010",
        "24V": "05013"
      },
      "od_max": 20,
      "cavi_ids": [
        "30A_3c_Y"
      ],
      "hawse_ids": [
        "04049-CRM",
        "04050"
      ],
      "cont_ids": [
        "85424",
        "85420"
      ]
    },
    "CM7": {
      "label": "CM7",
      "desc": "Cablemaster CM-7",
      "sub": "Cavo Ø 20–32mm · 12V o 24V DC",
      "tensioni": {
        "12V": "04020",
        "24V": "04022",
        "24V s/HP": "4022NOHP"
      },
      "od_max": 32,
      "cavi_ids": [
        "50A_3c_Y",
        "50A_4c_Y",
        "50A_4c_W",
        "63A_3c_Y",
        "63A_4c_Y"
      ],
      "hawse_ids": [
        "04050",
        "04079-CRM"
      ],
      "cont_ids": [
        "85420",
        "85421"
      ]
    },
    "CM8": {
      "label": "CM8",
      "desc": "Cablemaster CM-8",
      "sub": "Cavo Ø 32–42mm (50mm con kit) · 24V DC",
      "tensioni": {
        "24V": "04091",
        "24V s/HP": "4091NOHP"
      },
      "od_max": 42,
      "cavi_ids": [
        "100A_4c_W",
        "100A_5c_W",
        "100A_3c_Y_iso"
      ],
      "hawse_ids": [
        "04093"
      ],
      "cont_ids": [
        "85425",
        "85480"
      ],
      "note": "Kit 04041 necessario per cavi 5 poli."
    },
    "CM9": {
      "label": "CM9",
      "desc": "Cablemaster CM-9",
      "sub": "Cavo Ø 38–58mm · 24V DC",
      "tensioni": {
        "24V c/HP": "4097-25-24",
        "24V s/HP": "4097-21-24"
      },
      "od_max": 58,
      "cavi_ids": [
        "150A_2awg_4c",
        "177A_1-0awg_4c",
        "200A_1-0awg_4c"
      ],
      "hawse_ids": [
        "04093",
        "04097-6"
      ],
      "cont_ids": [
        "85480"
      ]
    }
  },
  "cavi": {
    "30A_3c_Y": {
      "d": "30A · 3×6mm² · Giallo",
      "spec": "#10 AWG · 3 cond. STOW · Ø 16.9mm",
      "od": 16.9,
      "amp": 30,
      "poli": 3,
      "col": "Giallo",
      "mkt": "USA",
      "p": "94006",
      "lun": [
        {
          "m": 15,
          "c": "SC94004-15"
        },
        {
          "m": 20,
          "c": "SC14179-20",
          "n": "scatola"
        },
        {
          "m": 25,
          "c": "SC14179-25"
        },
        {
          "m": 30,
          "c": "SC14179-30"
        }
      ],
      "conn": "CONN_30A",
      "attrs": {
        "amp": 30,
        "od": 16.9,
        "poli": 3,
        "col": "Giallo",
        "mercato": [
          "USA"
        ],
        "lunghezze_m": [
          15,
          20,
          25,
          30
        ],
        "gruppo_conn": "CONN_30A",
        "famiglia": "30A"
      }
    },
    "50A_3c_Y": {
      "d": "50A · 3×12mm² · Giallo",
      "spec": "#6 AWG · 3 cond. STOW · Ø 25.4mm",
      "od": 25.4,
      "amp": 50,
      "poli": 3,
      "col": "Giallo",
      "mkt": "USA+EU",
      "p": "94004",
      "lun": [
        {
          "m": 15,
          "c": "SC94004-15"
        },
        {
          "m": 20,
          "c": "SC94004-20"
        },
        {
          "m": 25,
          "c": "SC94004-25"
        },
        {
          "m": 30,
          "c": "SC94004-30"
        },
        {
          "m": 60,
          "c": "SC94004-60"
        },
        {
          "m": 120,
          "c": "SC94004-120"
        }
      ],
      "conn": "CONN_50A_3P",
      "attrs": {
        "amp": 50,
        "od": 25.4,
        "poli": 3,
        "col": "Giallo",
        "mercato": [
          "USA",
          "EU"
        ],
        "lunghezze_m": [
          15,
          20,
          25,
          30,
          60,
          120
        ],
        "gruppo_conn": "CONN_50A_3P",
        "famiglia": "50A"
      }
    },
    "50A_4c_Y": {
      "d": "50A · 4×12mm² · Giallo",
      "spec": "#6 AWG · 4 cond. STOW · Ø 28.4mm",
      "od": 28.4,
      "amp": 50,
      "poli": 4,
      "col": "Giallo",
      "mkt": "USA+EU",
      "p": "94005",
      "lun": [
        {
          "m": 15,
          "c": "94005-15"
        },
        {
          "m": 20,
          "c": "SC94005"
        },
        {
          "m": 30,
          "c": "SC94005-30"
        },
        {
          "m": 60,
          "c": "SC94005-60"
        }
      ],
      "conn": "CONN_50A_4P",
      "attrs": {
        "amp": 50,
        "od": 28.4,
        "poli": 4,
        "col": "Giallo",
        "mercato": [
          "USA",
          "EU"
        ],
        "lunghezze_m": [
          15,
          20,
          30,
          60
        ],
        "gruppo_conn": "CONN_50A_4P",
        "famiglia": "50A"
      }
    },
    "50A_4c_W": {
      "d": "50A · 4×12mm² · Bianco",
      "spec": "#6 AWG · 4 cond. STOW · Ø 28.4mm",
      "od": 28.4,
      "amp": 50,
      "poli": 4,
      "col": "Bianco",
      "mkt": "USA+EU",
      "p": "94007",
      "lun": [
        {
          "m": 20,
          "c": "SC94007-20"
        },
        {
          "m": 25,
          "c": "SC94008-25"
        }
      ],
      "conn": "CONN_50A_4P",
      "attrs": {
        "amp": 50,
        "od": 28.4,
        "poli": 4,
        "col": "Bianco",
        "mercato": [
          "USA",
          "EU"
        ],
        "lunghezze_m": [
          20,
          25
        ],
        "gruppo_conn": "CONN_50A_4P",
        "famiglia": "50A"
      }
    },
    "63A_3c_Y": {
      "d": "63A · 3×16mm² · Giallo (EU)",
      "spec": "#4 AWG · 3 cond. SEOOW RoHS · Ø 22.4mm",
      "od": 22.4,
      "amp": 63,
      "poli": 3,
      "col": "Giallo",
      "mkt": "EU",
      "p": "94031-Y",
      "lun": [
        {
          "m": 20,
          "c": "94031Y-20"
        },
        {
          "m": 40,
          "c": "94031Y-40"
        },
        {
          "m": 60,
          "c": "94031Y-60"
        },
        {
          "m": 80,
          "c": "94031Y-80"
        }
      ],
      "conn": "CONN_63A",
      "attrs": {
        "amp": 63,
        "od": 22.4,
        "poli": 3,
        "col": "Giallo",
        "mercato": [
          "EU"
        ],
        "lunghezze_m": [
          20,
          40,
          60,
          80
        ],
        "gruppo_conn": "CONN_63A",
        "famiglia": "63A"
      }
    },
    "63A_4c_Y": {
      "d": "63A · 4×16mm² · Giallo",
      "spec": "#4 AWG · 4 cond. SEOOW · Ø 28mm",
      "od": 28,
      "amp": 63,
      "poli": 4,
      "col": "Giallo",
      "mkt": "EU",
      "p": "69598G",
      "lun": [
        {
          "m": 20,
          "c": "69598G-20"
        },
        {
          "m": 60,
          "c": "69598G-60"
        }
      ],
      "conn": "CONN_63A",
      "attrs": {
        "amp": 63,
        "od": 28.0,
        "poli": 4,
        "col": "Giallo",
        "mercato": [
          "EU"
        ],
        "lunghezze_m": [
          20,
          60
        ],
        "gruppo_conn": "CONN_63A",
        "famiglia": "63A"
      }
    },
    "100A_4c_W": {
      "d": "100A · 4×35mm² · Bianco",
      "spec": "#2 AWG · 4 cond. STOW · Ø 35.3mm",
      "od": 35.3,
      "amp": 100,
      "poli": 4,
      "col": "Bianco",
      "mkt": "USA+EU",
      "p": "94014-W",
      "lun": [
        {
          "m": 20,
          "c": "94014-W-20"
        },
        {
          "m": 25,
          "c": "94014-W-25"
        },
        {
          "m": 30,
          "c": "94014-W-30"
        },
        {
          "m": 35,
          "c": "94014-W-35"
        },
        {
          "m": 45,
          "c": "94014-W-45"
        }
      ],
      "conn": "CONN_100A_4P",
      "attrs": {
        "amp": 100,
        "od": 35.3,
        "poli": 4,
        "col": "Bianco",
        "mercato": [
          "USA",
          "EU"
        ],
        "lunghezze_m": [
          20,
          25,
          30,
          35,
          45
        ],
        "gruppo_conn": "CONN_100A_4P",
        "famiglia": "100A"
      }
    },
    "100A_5c_W": {
      "d": "100A · 5×35mm² · Bianco (3PH)",
      "spec": "#2 AWG · 5 cond. · Ø 40.5mm",
      "od": 40.5,
      "amp": 100,
      "poli": 5,
      "col": "Bianco",
      "mkt": "USA+EU",
      "p": "SC37110",
      "lun": [
        {
          "m": 20,
          "c": "SC37110"
        },
        {
          "m": 40,
          "c": "94017-Y-40",
          "n": "giallo"
        }
      ],
      "conn": "CONN_100A_5P",
      "note": "Kit 04041 obbligatorio per CM8.",
      "attrs": {
        "amp": 100,
        "od": 40.5,
        "poli": 5,
        "col": "Bianco",
        "mercato": [
          "USA",
          "EU"
        ],
        "lunghezze_m": [
          20,
          40
        ],
        "gruppo_conn": "CONN_100A_5P",
        "famiglia": "100A",
        "richiede_kit": "04041"
      }
    },
    "100A_3c_Y_iso": {
      "d": "100A · 3×35mm² · Giallo (IsoTrans)",
      "spec": "#2 AWG · 3 cond. STOW · Ø 31.8mm",
      "od": 31.8,
      "amp": 100,
      "poli": 3,
      "col": "Giallo",
      "mkt": "USA",
      "p": "94013-Y",
      "lun": [
        {
          "m": 20,
          "c": "94013-20MT"
        },
        {
          "m": 25,
          "c": "94013-25MT"
        }
      ],
      "conn": "CONN_100A_4P",
      "note": "Solo per trasformatori di isolamento — NO NEUTRO.",
      "attrs": {
        "amp": 100,
        "od": 31.8,
        "poli": 3,
        "col": "Giallo",
        "mercato": [
          "USA"
        ],
        "lunghezze_m": [
          20,
          25
        ],
        "gruppo_conn": "CONN_100A_4P",
        "famiglia": "100A"
      }
    },
    "150A_2awg_4c": {
      "d": "150A · 2AWG Type W · Nero",
      "spec": "2 AWG · 4 cond. Vu-Tron® · Ø 36.5mm",
      "od": 36.5,
      "amp": 150,
      "poli": 4,
      "col": "Nero",
      "mkt": "USA+EU",
      "p": "81664",
      "lun": [
        {
          "m": 25,
          "c": "81664-25"
        },
        {
          "m": 30,
          "c": "81664-30"
        },
        {
          "m": 60,
          "c": "81664-60"
        }
      ],
      "conn": "CONN_150A",
      "attrs": {
        "amp": 150,
        "od": 36.5,
        "poli": 4,
        "col": "Nero",
        "mercato": [
          "USA",
          "EU"
        ],
        "lunghezze_m": [
          25,
          30,
          60
        ],
        "gruppo_conn": "CONN_150A",
        "famiglia": "150A"
      }
    },
    "177A_1-0awg_4c": {
      "d": "177A · 1/0AWG Type W · Giallo",
      "spec": "1/0 AWG · 4 cond. · Ø 45.2mm",
      "od": 45.2,
      "amp": 177,
      "poli": 4,
      "col": "Giallo",
      "mkt": "USA+EU",
      "p": "SC81374",
      "lun": [
        {
          "m": 30,
          "c": "SC81374-30",
          "n": "Coleman"
        }
      ],
      "conn": "CONN_150A",
      "attrs": {
        "amp": 177,
        "od": 45.2,
        "poli": 4,
        "col": "Giallo",
        "mercato": [
          "USA",
          "EU"
        ],
        "lunghezze_m": [
          30
        ],
        "gruppo_conn": "CONN_150A",
        "famiglia": "177A"
      }
    },
    "200A_1-0awg_4c": {
      "d": "200A · 1/0AWG Type W · Nero",
      "spec": "1/0 AWG · 4 cond. · Ø 45.2mm",
      "od": 45.2,
      "amp": 200,
      "poli": 4,
      "col": "Nero",
      "mkt": "USA+EU",
      "p": "81384",
      "lun": [
        {
          "m": 20,
          "c": "81384-20"
        }
      ],
      "conn": "CONN_250A",
      "attrs": {
        "amp": 200,
        "od": 45.2,
        "poli": 4,
        "col": "Nero",
        "mercato": [
          "USA",
          "EU"
        ],
        "lunghezze_m": [
          20
        ],
        "gruppo_conn": "CONN_250A",
        "famiglia": "200A"
      }
    }
  },
  "connettori": {
    "CONN_30A": {
      "nome": "30A Hubbell (USA)",
      "spina": {
        "cod": "66817A",
        "d": "Spina maschio 30A 125V 2P+T",
        "marca": "Hubbell",
        "cap": "66818C"
      },
      "presa_v": {
        "cod": "99411",
        "d": "Presa femmina 30A 2P+T (volante)",
        "marca": "Hubbell"
      },
      "presa_f": {
        "cod": "99411",
        "d": "Inlet 30A 2P+T (pannello)",
        "marca": "Hubbell/Glendinning"
      },
      "attrs": {
        "amp_max": 30,
        "mercato": [
          "USA"
        ],
        "standard": "NEMA"
      }
    },
    "CONN_50A_3P": {
      "nome": "50A 3P+T Hubbell/Glendinning",
      "spina": {
        "cod": "99408",
        "d": "Spina maschio 50A 115/230V 3P+T",
        "marca": "Hubbell/Glendinning",
        "cap": "99410"
      },
      "presa_v": {
        "cod": "99413",
        "d": "Presa femmina 50A 4P (volante)",
        "marca": "Glendinning"
      },
      "presa_f": {
        "cod": "99413",
        "d": "Inlet 50A 4P (pannello)",
        "marca": "Glendinning"
      },
      "alt_sp": {
        "cod": "66778T",
        "d": "Spina alt. 50A 2P+T (monofase)",
        "marca": "Hubbell",
        "cap": "66822T"
      },
      "attrs": {
        "amp_max": 50,
        "mercato": [
          "USA",
          "EU"
        ],
        "standard": "Hubbell/Glendinning",
        "poli": 3
      }
    },
    "CONN_50A_4P": {
      "nome": "50A 4P Hubbell/Glendinning",
      "spina": {
        "cod": "99408",
        "d": "Spina maschio 50A 115/230V 3P+T",
        "marca": "Hubbell/Glendinning",
        "cap": "99410"
      },
      "presa_v": {
        "cod": "99413",
        "d": "Presa femmina 50A 4P (volante)",
        "marca": "Glendinning"
      },
      "presa_f": {
        "cod": "99413",
        "d": "Inlet 50A 4P (pannello)",
        "marca": "Glendinning"
      },
      "alt_sp2": {
        "cod": "66787U",
        "d": "Spina alt. 63A 2P+T Hubbell (USA)",
        "marca": "Hubbell",
        "cap": "66771C"
      },
      "alt_sp3": {
        "cod": "66790G",
        "d": "Spina alt. 63A 3P+T Hubbell (USA)",
        "marca": "Hubbell",
        "cap": "66771C"
      },
      "attrs": {
        "amp_max": 50,
        "mercato": [
          "USA",
          "EU"
        ],
        "standard": "Hubbell/Glendinning",
        "poli": 4
      }
    },
    "CONN_63A": {
      "nome": "63A EU",
      "spina": {
        "cod": "66787U",
        "d": "Spina maschio 63A 115/230V 1PH 2P+T",
        "marca": "Hubbell",
        "cap": "66771C"
      },
      "presa_v": {
        "cod": "99439-P",
        "d": "Presa femmina 63A 3P (volante/inlet)",
        "marca": "Glendinning"
      },
      "presa_f": {
        "cod": "99439-P",
        "d": "Inlet 63A 3P (pannello)",
        "marca": "Glendinning"
      },
      "alt_sp": {
        "cod": "66790G",
        "d": "Spina alt. 63A 3P+T (1PH/3PH)",
        "marca": "Hubbell",
        "cap": "66771C"
      },
      "attrs": {
        "amp_max": 63,
        "mercato": [
          "EU"
        ],
        "standard": "IEC"
      }
    },
    "CONN_100A_4P": {
      "nome": "100A 4P Glendinning (USA)",
      "spina": {
        "cod": "99423",
        "d": "Spina maschio 100A 120/240V 3P+T (4P)",
        "marca": "Glendinning"
      },
      "presa_v": {
        "cod": "99423-C",
        "d": "Presa femmina 100A 4P (volante)",
        "marca": "Glendinning"
      },
      "presa_f": {
        "cod": "99423-INL",
        "d": "Inlet 100A 4P (pannello)",
        "marca": "Glendinning"
      },
      "alt_sp": {
        "cod": "1442A",
        "d": "Spina alt. 100A 230V 3P+T MKN (EU)",
        "marca": "MKN",
        "presa_v": {
          "cod": "1442A",
          "d": "Presa MKN 100A 230V"
        },
        "presa_f": {
          "cod": "1442A",
          "d": "Inlet MKN 100A 230V"
        }
      },
      "attrs": {
        "amp_max": 100,
        "mercato": [
          "USA",
          "EU"
        ],
        "standard": "Glendinning/MKN",
        "poli": 4
      }
    },
    "CONN_100A_5P": {
      "nome": "100A 5P Glendinning/MKN",
      "spina": {
        "cod": "99424P",
        "d": "Spina maschio 100A 208/230V 3PH 5P",
        "marca": "Glendinning"
      },
      "presa_v": {
        "cod": "99432",
        "d": "Presa femmina 100A 5P (volante)",
        "marca": "Glendinning"
      },
      "presa_f": {
        "cod": "99424-B9R",
        "d": "Inlet 100A 5P (pannello)",
        "marca": "Glendinning"
      },
      "alt_sp": {
        "cod": "3374",
        "d": "Spina alt. 100A 400V 3PH MKN (EU)",
        "marca": "MKN",
        "presa_v": {
          "cod": "99432",
          "d": "Presa Glendinning 5P"
        },
        "presa_f": {
          "cod": "99424-B9R",
          "d": "Inlet Glendinning 5P"
        }
      },
      "attrs": {
        "amp_max": 100,
        "mercato": [
          "USA",
          "EU"
        ],
        "standard": "Glendinning/MKN",
        "poli": 5
      }
    },
    "CONN_150A": {
      "nome": "150A Mennekes DS9",
      "spina": {
        "cod": "MCH3998013",
        "d": "Spina maschio 150A 380V 3PH DS9",
        "marca": "Mennekes",
        "cap": "MCH319A013"
      },
      "presa_v": {
        "cod": "99432",
        "d": "Presa femmina 100A 5P Glendinning (adattatore)",
        "marca": "Glendinning"
      },
      "presa_f": {
        "cod": "99424-B9R",
        "d": "Inlet 100A 5P pannello (adattatore)",
        "marca": "Glendinning"
      },
      "attrs": {
        "amp_max": 150,
        "mercato": [
          "EU"
        ],
        "standard": "Mennekes DS9"
      }
    },
    "CONN_250A": {
      "nome": "250A Mennekes DS2",
      "spina": {
        "cod": "MEMR3928013",
        "d": "Spina maschio 250A 400V 3PH DS2",
        "marca": "Mennekes",
        "cap": "MEMR392A913"
      },
      "presa_v": {
        "cod": "MEMR3928017",
        "d": "Presa femmina 250A 400V 3PH DS2",
        "marca": "Mennekes"
      },
      "presa_f": {
        "cod": "MEMR3928017",
        "d": "Inlet 250A DS2 (pannello)",
        "marca": "Mennekes"
      },
      "note": "Sezione frontale + impugnatura posteriore separati.",
      "attrs": {
        "amp_max": 250,
        "mercato": [
          "EU"
        ],
        "standard": "Mennekes DS2"
      }
    }
  },
  "hawse": {
    "04049-CRM": {
      "d": "Hawse Pipe inox 16/30A",
      "c": "04049-CRM",
      "od": 20,
      "motori": [
        "CM4"
      ],
      "attrs": {
        "od_max": 20,
        "motori": [
          "CM4"
        ]
      }
    },
    "04050": {
      "d": "Bocchettone CM-4/7 SS",
      "c": "04050",
      "od": 29,
      "motori": [
        "CM4",
        "CM7"
      ],
      "attrs": {
        "od_max": 29,
        "motori": [
          "CM4",
          "CM7"
        ]
      }
    },
    "04079-CRM": {
      "d": "Hawse Pipe SS + Guide Roller 50/63A",
      "c": "04079-CRM",
      "od": 29,
      "motori": [
        "CM7"
      ],
      "attrs": {
        "od_max": 29,
        "motori": [
          "CM7"
        ]
      }
    },
    "04093": {
      "d": "Kit Hawse Pipe CM8/CM9 alluminio",
      "c": "04093",
      "od": 50,
      "motori": [
        "CM8",
        "CM9"
      ],
      "note": "Std Ø42mm / 50mm con kit 04041.",
      "attrs": {
        "od_max": 50,
        "motori": [
          "CM8",
          "CM9"
        ]
      }
    },
    "04097-6": {
      "d": "Hawse Pipe CM9 alluminio Ø190mm",
      "c": "04097-6",
      "od": 58,
      "motori": [
        "CM9"
      ],
      "note": "ID Ø190mm · L 328mm.",
      "attrs": {
        "od_max": 58,
        "motori": [
          "CM9"
        ]
      }
    }
  },
  "contenitori": {
    "85424": {
      "d": "Contenitore 18\"×18\"",
      "dim": "Ø 457 × H 457mm",
      "c": "85424",
      "motori": [
        "CM4"
      ],
      "attrs": {
        "motori": [
          "CM4"
        ]
      }
    },
    "85420": {
      "d": "Contenitore CM-4/7",
      "dim": "Ø 560 × H 380mm",
      "c": "85420",
      "motori": [
        "CM4",
        "CM7"
      ],
      "attrs": {
        "motori": [
          "CM4",
          "CM7"
        ]
      }
    },
    "85421": {
      "d": "Contenitore CM-7 (alt.)",
      "dim": "Ø 560 × H 380mm",
      "c": "85421",
      "motori": [
        "CM7"
      ],
      "attrs": {
        "motori": [
          "CM7"
        ]
      }
    },
    "85425": {
      "d": "Contenitore CM-8",
      "dim": "Ø 560 × H 560mm",
      "c": "85425",
      "motori": [
        "CM8"
      ],
      "attrs": {
        "motori": [
          "CM8"
        ]
      }
    },
    "85480": {
      "d": "Contenitore CM-8/9 grande",
      "dim": "Ø 635 × H 877mm",
      "c": "85480",
      "motori": [
        "CM8",
        "CM9"
      ],
      "note": "Tagliabile a H 610mm.",
      "attrs": {
        "motori": [
          "CM8",
          "CM9"
        ]
      }
    }
  },
  "catalogo": [
    {
      "cat": "Motore",
      "cod": "05010",
      "d": "Cablemaster CM-4 · 12V",
      "attivo": true,
      "sostituito_da": null
    },
    {
      "cat": "Motore",
      "cod": "05013",
      "d": "Cablemaster CM-4 · 24V",
      "attivo": true,
      "sostituito_da": null
    },
    {
      "cat": "Motore",
      "cod": "04020",
      "d": "Cablemaster CM-7 · 12V",
      "attivo": true,
      "sostituito_da": null
    },
    {
      "cat": "Motore",
      "cod": "04022",
      "d": "Cablemaster CM-7 · 24V",
      "attivo": true,
      "sostituito_da": null
    },
    {
      "cat": "Motore",
      "cod": "4022NOHP",
      "d": "Cablemaster CM-7 · 24V (senza HP)",
      "attivo": true,
      "sostituito_da": null
    },
    {
      "cat": "Motore",
      "cod": "04091",
      "d": "Cablemaster CM-8 · 24V",
      "attivo": true,
      "sostituito_da": null
    },
    {
      "cat": "Motore",
      "cod": "4091NOHP",
      "d": "Cablemaster CM-8 · 24V (senza HP)",
      "attivo": true,
      "sostituito_da": null
    },
    {
      "cat": "Motore",
      "cod": "4097-25-24",
      "d": "Cablemaster CM-9 · 24V con HP",
      "attivo": true,
      "sostituito_da": null
    },
    {
      "cat": "Motore",
      "cod": "4097-21-24",
      "d": "Cablemaster CM-9 · 24V senza HP",
      "attivo": true,
      "sostituito_da": null
    },
    {
      "cat": "Cavo",
      "cod": "SC94004-15",
      "d": "Cavo 50A 3×12mm² Giallo · 15m",
      "attivo": true,
      "sostituito_da": null
    },
    {
      "cat": "Cavo",
      "cod": "SC94004-20",
      "d": "Cavo 50A 3×12mm² Giallo · 20m",
      "attivo": true,
      "sostituito_da": null
    },
    {
      "cat": "Cavo",
      "cod": "SC94004-25",
      "d": "Cavo 50A 3×12mm² Giallo · 25m",
      "attivo": true,
      "sostituito_da": null
    },
    {
      "cat": "Cavo",
      "cod": "SC94004-30",
      "d": "Cavo 50A 3×12mm² Giallo · 30m",
      "attivo": true,
      "sostituito_da": null
    },
    {
      "cat": "Cavo",
      "cod": "SC94004-60",
      "d": "Cavo 50A 3×12mm² Giallo · 60m",
      "attivo": true,
      "sostituito_da": null
    },
    {
      "cat": "Cavo",
      "cod": "SC94004-120",
      "d": "Cavo 50A 3×12mm² Giallo · 120m",
      "attivo": true,
      "sostituito_da": null
    },
    {
      "cat": "Cavo",
      "cod": "94005-15",
      "d": "Cavo 50A 4×12mm² Giallo · 15m",
      "attivo": true,
      "sostituito_da": null
    },
    {
      "cat": "Cavo",
      "cod": "SC94005",
      "d": "Cavo 50A 4×12mm² Giallo · 20m",
      "attivo": true,
      "sostituito_da": null
    },
    {
      "cat": "Cavo",
      "cod": "SC94005-30",
      "d": "Cavo 50A 4×12mm² Giallo · 30m",
      "attivo": true,
      "sostituito_da": null
    },
    {
      "cat": "Cavo",
      "cod": "SC94005-60",
      "d": "Cavo 50A 4×12mm² Giallo · 60m",
      "attivo": true,
      "sostituito_da": null
    },
    {
      "cat": "Cavo",
      "cod": "SC94007-20",
      "d": "Cavo 50A 4×12mm² Bianco · 20m",
      "attivo": true,
      "sostituito_da": null
    },
    {
      "cat": "Cavo",
      "cod": "SC94008-25",
      "d": "Cavo 50A 4×12mm² Bianco · 25m",
      "attivo": true,
      "sostituito_da": null
    },
    {
      "cat": "Cavo",
      "cod": "94031Y-20",
      "d": "Cavo 63A 3×16mm² Giallo EU · 20m",
      "attivo": true,
      "sostituito_da": null
    },
    {
      "cat": "Cavo",
      "cod": "94031Y-40",
      "d": "Cavo 63A 3×16mm² Giallo EU · 40m",
      "attivo": true,
      "sostituito_da": null
    },
    {
      "cat": "Cavo",
      "cod": "94031Y-60",
      "d": "Cavo 63A 3×16mm² Giallo EU · 60m",
      "attivo": true,
      "sostituito_da": null
    },
    {
      "cat": "Cavo",
      "cod": "94031Y-80",
      "d": "Cavo 63A 3×16mm² Giallo EU · 80m",
      "attivo": true,
      "sostituito_da": null
    },
    {
      "cat": "Cavo",
      "cod": "69598G-20",
      "d": "Cavo 63A 4×16mm² Giallo · 20m",
      "attivo": true,
      "sostituito_da": null
    },
    {
      "cat": "Cavo",
      "cod": "94013-20MT",
      "d": "Cavo 100A 3×35mm² IsoTrans · 20m",
      "attivo": true,
      "sostituito_da": null
    },
    {
      "cat": "Cavo",
      "cod": "94014-W-20",
      "d": "Cavo 100A 4×35mm² Bianco · 20m",
      "attivo": true,
      "sostituito_da": null
    },
    {
      "cat": "Cavo",
      "cod": "94014-W-25",
      "d": "Cavo 100A 4×35mm² Bianco · 25m",
      "attivo": true,
      "sostituito_da": null
    },
    {
      "cat": "Cavo",
      "cod": "94014-W-30",
      "d": "Cavo 100A 4×35mm² Bianco · 30m",
      "attivo": true,
      "sostituito_da": null
    },
    {
      "cat": "Cavo",
      "cod": "94014-W-35",
      "d": "Cavo 100A 4×35mm² Bianco · 35m",
      "attivo": true,
      "sostituito_da": null
    },
    {
      "cat": "Cavo",
      "cod": "94014-W-45",
      "d": "Cavo 100A 4×35mm² Bianco · 45m",
      "attivo": true,
      "sostituito_da": null
    },
    {
      "cat": "Cavo",
      "cod": "SC37110",
      "d": "Cavo 100A 5×35mm² Bianco 3PH · 20m",
      "attivo": true,
      "sostituito_da": null
    },
    {
      "cat": "Cavo",
      "cod": "94017-Y-40",
      "d": "Cavo 100A 5P Giallo · 40m",
      "attivo": true,
      "sostituito_da": null
    },
    {
      "cat": "Cavo",
      "cod": "81664-25",
      "d": "Cavo 150A 2AWG Type W · 25m",
      "attivo": true,
      "sostituito_da": null
    },
    {
      "cat": "Cavo",
      "cod": "81664-30",
      "d": "Cavo 150A 2AWG Type W · 30m",
      "attivo": true,
      "sostituito_da": null
    },
    {
      "cat": "Cavo",
      "cod": "81664-60",
      "d": "Cavo 150A 2AWG Type W · 60m",
      "attivo": true,
      "sostituito_da": null
    },
    {
      "cat": "Cavo",
      "cod": "SC81374-30",
      "d": "Cavo 177A 1/0AWG Type W · 30m",
      "attivo": true,
      "sostituito_da": null
    },
    {
      "cat": "Cavo",
      "cod": "81384-20",
      "d": "Cavo 200A 1/0AWG Type W · 20m",
      "attivo": true,
      "sostituito_da": null
    },
    {
      "cat": "Spina",
      "cod": "66817A",
      "d": "Spina 30A 125V 2P+T Hubbell",
      "attivo": true,
      "sostituito_da": null
    },
    {
      "cat": "Spina",
      "cod": "66818C",
      "d": "Cappuccio spina 30A Hubbell",
      "attivo": true,
      "sostituito_da": null
    },
    {
      "cat": "Spina",
      "cod": "66778T",
      "d": "Spina 50A 115/230V 2P+T Hubbell",
      "attivo": true,
      "sostituito_da": null
    },
    {
      "cat": "Spina",
      "cod": "66822T",
      "d": "Cappuccio 50A 2P+T",
      "attivo": true,
      "sostituito_da": null
    },
    {
      "cat": "Spina",
      "cod": "99408",
      "d": "Spina 50A 115/230V 3P+T Hubbell/Glendinning",
      "attivo": true,
      "sostituito_da": null
    },
    {
      "cat": "Spina",
      "cod": "99410",
      "d": "Cappuccio 50A 3P+T",
      "attivo": true,
      "sostituito_da": null
    },
    {
      "cat": "Spina",
      "cod": "66787U",
      "d": "Spina 63A 115/230V 1PH 2P+T Hubbell",
      "attivo": true,
      "sostituito_da": null
    },
    {
      "cat": "Spina",
      "cod": "66790G",
      "d": "Spina 63A 115/230V 3P+T Hubbell",
      "attivo": true,
      "sostituito_da": null
    },
    {
      "cat": "Spina",
      "cod": "66771C",
      "d": "Cappuccio 63A Hubbell",
      "attivo": true,
      "sostituito_da": null
    },
    {
      "cat": "Spina",
      "cod": "99437",
      "d": "Spina 32A 2P+T EU",
      "attivo": true,
      "sostituito_da": null
    },
    {
      "cat": "Spina",
      "cod": "99423",
      "d": "Spina 100A 120/240V 3P+T Glendinning (4P)",
      "attivo": true,
      "sostituito_da": null
    },
    {
      "cat": "Spina",
      "cod": "99424P",
      "d": "Spina 100A 208/230V 3PH 5P Glendinning",
      "attivo": true,
      "sostituito_da": null
    },
    {
      "cat": "Spina",
      "cod": "1442A",
      "d": "Spina 100A 230V 3P+T MKN · EU",
      "attivo": true,
      "sostituito_da": null
    },
    {
      "cat": "Spina",
      "cod": "3374",
      "d": "Spina 100A 400V 3PH 3P+T MKN · EU",
      "attivo": true,
      "sostituito_da": null
    },
    {
      "cat": "Spina",
      "cod": "MCH3998013",
      "d": "Spina 150A DS9 380V 3PH Mennekes",
      "attivo": true,
      "sostituito_da": null
    },
    {
      "cat": "Spina",
      "cod": "MCH319A013",
      "d": "Impugnatura DS9 neoprenex",
      "attivo": true,
      "sostituito_da": null
    },
    {
      "cat": "Spina",
      "cod": "MEMR3928013",
      "d": "Spina 250A DS2 400V 3PH Mennekes",
      "attivo": true,
      "sostituito_da": null
    },
    {
      "cat": "Spina",
      "cod": "MEMR392A913",
      "d": "Impugnatura DS2",
      "attivo": true,
      "sostituito_da": null
    },
    {
      "cat": "Inlet/Presa",
      "cod": "99411",
      "d": "Inlet 30A 2P+T Glendinning",
      "attivo": true,
      "sostituito_da": null
    },
    {
      "cat": "Inlet/Presa",
      "cod": "99413",
      "d": "Presa/Inlet 50A 4P Glendinning",
      "attivo": true,
      "sostituito_da": null
    },
    {
      "cat": "Inlet/Presa",
      "cod": "99439-P",
      "d": "Presa 63A 3P EU Glendinning",
      "attivo": true,
      "sostituito_da": null
    },
    {
      "cat": "Inlet/Presa",
      "cod": "99423-C",
      "d": "Presa femmina 100A 4P Glendinning",
      "attivo": true,
      "sostituito_da": null
    },
    {
      "cat": "Inlet/Presa",
      "cod": "99423-INL",
      "d": "Inlet 100A 4P pannello",
      "attivo": true,
      "sostituito_da": null
    },
    {
      "cat": "Inlet/Presa",
      "cod": "99432",
      "d": "Presa femmina 100A 5P Glendinning",
      "attivo": true,
      "sostituito_da": null
    },
    {
      "cat": "Inlet/Presa",
      "cod": "99424-B9R",
      "d": "Inlet 100A 5P pannello",
      "attivo": true,
      "sostituito_da": null
    },
    {
      "cat": "Inlet/Presa",
      "cod": "MEMR3928017",
      "d": "Presa/Inlet 250A DS2 Mennekes 3P+T+N",
      "attivo": true,
      "sostituito_da": null
    },
    {
      "cat": "Hawse",
      "cod": "04049-CRM",
      "d": "Hawse Pipe inox 16/30A",
      "attivo": true,
      "sostituito_da": null
    },
    {
      "cat": "Hawse",
      "cod": "04050",
      "d": "Bocchettone CM-4/7 SS",
      "attivo": true,
      "sostituito_da": null
    },
    {
      "cat": "Hawse",
      "cod": "04079-CRM",
      "d": "Hawse Pipe SS + Guide Roller 50/63A",
      "attivo": true,
      "sostituito_da": null
    },
    {
      "cat": "Hawse",
      "cod": "04093",
      "d": "Hawse Pipe CM8/CM9 alluminio",
      "attivo": true,
      "sostituito_da": null
    },
    {
      "cat": "Hawse",
      "cod": "04097-6",
      "d": "Hawse Pipe CM9 Ø190mm",
      "attivo": true,
      "sostituito_da": null
    },
    {
      "cat": "Contenitore",
      "cod": "85424",
      "d": "Contenitore 18\"×18\" · Ø457×H457mm",
      "attivo": true,
      "sostituito_da": null
    },
    {
      "cat": "Contenitore",
      "cod": "85420",
      "d": "Contenitore CM-4/7 · Ø560×H380mm",
      "attivo": true,
      "sostituito_da": null
    },
    {
      "cat": "Contenitore",
      "cod": "85421",
      "d": "Contenitore CM-7 alt. · Ø560×H380mm",
      "attivo": true,
      "sostituito_da": null
    },
    {
      "cat": "Contenitore",
      "cod": "85425",
      "d": "Contenitore CM-8 · Ø560×H560mm",
      "attivo": true,
      "sostituito_da": null
    },
    {
      "cat": "Contenitore",
      "cod": "85480",
      "d": "Contenitore CM-8/9 grande · Ø635×H877mm",
      "attivo": true,
      "sostituito_da": null
    },
    {
      "cat": "Accessorio",
      "cod": "04041",
      "d": "Kit conversione rulli CM-8 per cavo 5 poli",
      "attivo": true,
      "sostituito_da": null
    },
    {
      "cat": "Accessorio",
      "cod": "04040",
      "d": "Pipe End Roller Assembly",
      "attivo": true,
      "sostituito_da": null
    },
    {
      "cat": "Accessorio",
      "cod": "04043",
      "d": "Kit prolunga orizzontale CM-7",
      "attivo": true,
      "sostituito_da": null
    },
    {
      "cat": "Accessorio",
      "cod": "04044",
      "d": "Kit prolunga verticale CM-7/CM8",
      "attivo": true,
      "sostituito_da": null
    },
    {
      "cat": "Accessorio",
      "cod": "04054",
      "d": "Guide Roller Assembly (no switch)",
      "attivo": true,
      "sostituito_da": null
    },
    {
      "cat": "Accessorio",
      "cod": "04070",
      "d": "Low Profile Bracket Assembly CM8",
      "attivo": true,
      "sostituito_da": null
    },
    {
      "cat": "Accessorio",
      "cod": "50006",
      "d": "Staffa montaggio superiore",
      "attivo": true,
      "sostituito_da": null
    },
    {
      "cat": "Accessorio",
      "cod": "04052",
      "d": "Pipe Clamp Assembly",
      "attivo": true,
      "sostituito_da": null
    },
    {
      "cat": "Accessorio",
      "cod": "04062",
      "d": "Angling Assembly 30°",
      "attivo": true,
      "sostituito_da": null
    },
    {
      "cat": "Accessorio",
      "cod": "04066",
      "d": "Angling Assembly 90°",
      "attivo": true,
      "sostituito_da": null
    },
    {
      "cat": "Accessorio",
      "cod": "04067",
      "d": "Angling Assembly 150°",
      "attivo": true,
      "sostituito_da": null
    },
    {
      "cat": "Guida rulli",
      "cod": "4075-30-18",
      "d": "Guida rulli 30A 18\"",
      "attivo": true,
      "sostituito_da": null
    },
    {
      "cat": "Guida rulli",
      "cod": "4075-50-18",
      "d": "Guida rulli 50A 18\"",
      "attivo": true,
      "sostituito_da": null
    },
    {
      "cat": "Guida rulli",
      "cod": "4075-50-36",
      "d": "Guida rulli 50A 36\"",
      "attivo": true,
      "sostituito_da": null
    },
    {
      "cat": "Guida rulli",
      "cod": "4075-50-36H",
      "d": "Guida rulli 50A 36\" orizzontale",
      "attivo": true,
      "sostituito_da": null
    },
    {
      "cat": "Guida rulli",
      "cod": "4075-50-36V",
      "d": "Guida rulli 50A 36\" verticale",
      "attivo": true,
      "sostituito_da": null
    },
    {
      "cat": "Guida rulli",
      "cod": "4075-50-60",
      "d": "Guida rulli 50A 60\"",
      "attivo": true,
      "sostituito_da": null
    },
    {
      "cat": "Guida rulli",
      "cod": "4075-50-66",
      "d": "Guida rulli 50A 66\"",
      "attivo": true,
      "sostituito_da": null
    },
    {
      "cat": "Controllo",
      "cod": "04155",
      "d": "Kit radiocomando 12/24V — 1 rx + 2 tx",
      "attivo": true,
      "sostituito_da": null
    },
    {
      "cat": "Controllo",
      "cod": "04154-1B",
      "d": "Remote Control (ricambio)",
      "attivo": true,
      "sostituito_da": null
    },
    {
      "cat": "Controllo",
      "cod": "04153",
      "d": "Filtro interferenze",
      "attivo": true,
      "sostituito_da": null
    },
    {
      "cat": "Pipe/Tubo",
      "cod": "42007-100",
      "d": "Tubo PVC 3\" · L 1.00m",
      "attivo": true,
      "sostituito_da": null
    },
    {
      "cat": "Pipe/Tubo",
      "cod": "42007-120",
      "d": "Tubo PVC 3\" · L 1.20m",
      "attivo": true,
      "sostituito_da": null
    }
  ],
  "kit_preset": [
    {
      "id": "p1",
      "name": "CM4 · 30A · USA · 12V · 15m",
      "desc": "Kit compatto 30A monofase USA.",
      "tags": [
        "CM4",
        "30A",
        "USA",
        "12V"
      ],
      "bom": [
        {
          "cat": "Avvolgicavo",
          "cod": "05010",
          "d": "Cablemaster CM-4 · 12V",
          "qty": 1
        },
        {
          "cat": "Cavo",
          "cod": "SC94004-15",
          "d": "Cavo 30A 3×6mm² Giallo · 15m",
          "qty": 1
        },
        {
          "cat": "Spina",
          "cod": "66817A",
          "d": "Spina 30A 125V 2P+T · Hubbell",
          "qty": 1
        },
        {
          "cat": "Cappuccio",
          "cod": "66818C",
          "d": "Cappuccio 30A Hubbell",
          "qty": 1
        },
        {
          "cat": "Inlet bordo",
          "cod": "99411",
          "d": "Inlet 30A 2P+T Glendinning",
          "qty": 1
        },
        {
          "cat": "Hawse Pipe",
          "cod": "04050",
          "d": "Bocchettone CM-4/7 SS",
          "qty": 1
        },
        {
          "cat": "Contenitore",
          "cod": "85424",
          "d": "Contenitore 18\"×18\"",
          "qty": 1
        }
      ]
    },
    {
      "id": "p2",
      "name": "CM7 · 50A · USA · 24V · 20m",
      "desc": "Kit CM7 50A trifase USA.",
      "tags": [
        "CM7",
        "50A",
        "USA",
        "24V"
      ],
      "bom": [
        {
          "cat": "Avvolgicavo",
          "cod": "04022",
          "d": "Cablemaster CM-7 · 24V",
          "qty": 1
        },
        {
          "cat": "Cavo",
          "cod": "SC94004-20",
          "d": "Cavo 50A 3×12mm² Giallo · 20m",
          "qty": 1
        },
        {
          "cat": "Spina",
          "cod": "99408",
          "d": "Spina 50A 115/230V 3P+T Hubbell",
          "qty": 1
        },
        {
          "cat": "Cappuccio",
          "cod": "99410",
          "d": "Cappuccio 50A 3P",
          "qty": 1
        },
        {
          "cat": "Inlet bordo",
          "cod": "99413",
          "d": "Inlet 50A 4P Glendinning",
          "qty": 1
        },
        {
          "cat": "Hawse Pipe",
          "cod": "04079-CRM",
          "d": "Hawse Pipe SS + Guide Roller",
          "qty": 1
        },
        {
          "cat": "Contenitore",
          "cod": "85420",
          "d": "Contenitore CM-7 · Ø560×H380mm",
          "qty": 1
        }
      ]
    },
    {
      "id": "p3",
      "name": "CM7 · 63A · EU · 24V · 20m",
      "desc": "Kit CM7 63A EU — cavo SEOOW RoHS.",
      "tags": [
        "CM7",
        "63A",
        "EU",
        "24V"
      ],
      "bom": [
        {
          "cat": "Avvolgicavo",
          "cod": "04022",
          "d": "Cablemaster CM-7 · 24V",
          "qty": 1
        },
        {
          "cat": "Cavo",
          "cod": "94031Y-20",
          "d": "Cavo 63A 3×16mm² Giallo EU · 20m",
          "qty": 1
        },
        {
          "cat": "Spina",
          "cod": "66787U",
          "d": "Spina 63A 115/230V 1PH 2P+T Hubbell",
          "qty": 1
        },
        {
          "cat": "Cappuccio",
          "cod": "66771C",
          "d": "Cappuccio 63A Hubbell",
          "qty": 1
        },
        {
          "cat": "Inlet bordo",
          "cod": "99439-P",
          "d": "Inlet 63A 3P Glendinning",
          "qty": 1
        },
        {
          "cat": "Hawse Pipe",
          "cod": "04079-CRM",
          "d": "Hawse Pipe SS + Guide Roller",
          "qty": 1
        },
        {
          "cat": "Contenitore",
          "cod": "85420",
          "d": "Contenitore CM-7 · Ø560×H380mm",
          "qty": 1
        },
        {
          "cat": "Radiocomando",
          "cod": "04155",
          "d": "Remote Control 12/24V · 2 trasmettitori",
          "qty": 1
        }
      ]
    },
    {
      "id": "p4",
      "name": "CM8 · 100A · USA · 24V · 25m",
      "desc": "Kit CM8 100A monofase USA.",
      "tags": [
        "CM8",
        "100A",
        "USA",
        "24V"
      ],
      "bom": [
        {
          "cat": "Avvolgicavo",
          "cod": "04091",
          "d": "Cablemaster CM-8 · 24V",
          "qty": 1
        },
        {
          "cat": "Cavo",
          "cod": "94014-W-25",
          "d": "Cavo 100A 4×35mm² Bianco · 25m",
          "qty": 1
        },
        {
          "cat": "Spina",
          "cod": "99423",
          "d": "Spina 100A 120/240V 3P+T Glendinning",
          "qty": 1
        },
        {
          "cat": "Inlet bordo",
          "cod": "99423-C",
          "d": "Presa 100A 4P femmina Glendinning",
          "qty": 1
        },
        {
          "cat": "Hawse Pipe",
          "cod": "04093",
          "d": "Kit Hawse Pipe CM8/CM9 alluminio",
          "qty": 1
        },
        {
          "cat": "Contenitore",
          "cod": "85425",
          "d": "Contenitore CM-8 · Ø560×H560mm",
          "qty": 1
        },
        {
          "cat": "Radiocomando",
          "cod": "04155",
          "d": "Remote Control",
          "qty": 1
        }
      ]
    },
    {
      "id": "p5",
      "name": "CM8 · 100A · EU · 24V · 5P · 20m",
      "desc": "Kit CM8 100A trifase EU 400V — 5 poli.",
      "tags": [
        "CM8",
        "100A",
        "EU",
        "24V",
        "3PH"
      ],
      "bom": [
        {
          "cat": "Avvolgicavo",
          "cod": "04091",
          "d": "Cablemaster CM-8 · 24V",
          "qty": 1
        },
        {
          "cat": "Cavo",
          "cod": "SC37110",
          "d": "Cavo 100A 5×35mm² Bianco · 20m",
          "qty": 1
        },
        {
          "cat": "Kit rulli 5P",
          "cod": "04041",
          "d": "Conversione rulli CM-8 per 5 poli",
          "qty": 1
        },
        {
          "cat": "Spina",
          "cod": "3374",
          "d": "Spina 100A 400V 3PH 3P+T MKN",
          "qty": 1
        },
        {
          "cat": "Inlet bordo",
          "cod": "99432",
          "d": "Presa 100A 5P femmina Glendinning",
          "qty": 1
        },
        {
          "cat": "Hawse Pipe",
          "cod": "04093",
          "d": "Kit Hawse Pipe CM8/CM9 alluminio",
          "qty": 1
        },
        {
          "cat": "Contenitore",
          "cod": "85480",
          "d": "Contenitore CM-8/9 grande",
          "qty": 1
        }
      ]
    },
    {
      "id": "p6",
      "name": "CM9 · 177A · 24V · 30m",
      "desc": "Kit CM9 alta corrente — Coleman Type W.",
      "tags": [
        "CM9",
        "177A",
        "24V"
      ],
      "bom": [
        {
          "cat": "Avvolgicavo",
          "cod": "4097-25-24",
          "d": "Cablemaster CM-9 · 24V con HP",
          "qty": 1
        },
        {
          "cat": "Cavo",
          "cod": "SC81374-30",
          "d": "Cavo 177A 1/0AWG Type W · 30m",
          "qty": 1
        },
        {
          "cat": "Spina",
          "cod": "MCH3998013",
          "d": "Spina 150A DS9 380V 3PH Mennekes",
          "qty": 1
        },
        {
          "cat": "Impugnatura spina",
          "cod": "MCH319A013",
          "d": "Impugnatura neoprenex DS9",
          "qty": 1
        },
        {
          "cat": "Inlet bordo",
          "cod": "99432",
          "d": "Presa 100A 5P femmina Glendinning",
          "qty": 1
        },
        {
          "cat": "Hawse Pipe",
          "cod": "04097-6",
          "d": "Hawse Pipe CM9 alluminio Ø190mm",
          "qty": 1
        },
        {
          "cat": "Contenitore",
          "cod": "85480",
          "d": "Contenitore CM-8/9 grande",
          "qty": 1
        }
      ]
    }
  ]
}